clubs_gym/__init__.py
clubs_gym/error.py
clubs_gym/agent/__init__.py
clubs_gym/agent/base.py
clubs_gym/agent/kuhn.py
clubs_gym/envs/__init__.py
clubs_gym/envs/env.py
clubs_gym-0.1.4.dist-info/LICENSE
clubs_gym-0.1.4.dist-info/METADATA
clubs_gym-0.1.4.dist-info/WHEEL
clubs_gym-0.1.4.dist-info/top_level.txt
clubs_gym-0.1.4.dist-info/RECORD
