Metadata-Version: 2.1
Name: clubs-gym
Version: 0.1.4
Summary: clubs is an open ai gym environment for running arbitrary poker configurations.
Home-page: https://github.com/fschlatt/clubs_gym
Author: Ferdinand Schlatt
License: GPL-3.0
Project-URL: Bug Reports, https://github.com/fschlatt/clubs_gym/issues
Project-URL: Source, https://github.com/fschlatt/clubs_gym/
Keywords: reinforcement learning,poker,AI,gym
Platform: UNKNOWN
Classifier: Development Status :: 3 - Alpha
Classifier: Intended Audience :: Developers
Classifier: Intended Audience :: Education
Classifier: Intended Audience :: Science/Research
Classifier: Topic :: Games/Entertainment
Classifier: Topic :: Scientific/Engineering :: Artificial Intelligence
Classifier: License :: OSI Approved :: GNU General Public License v3 (GPLv3)
Classifier: Programming Language :: Python :: 3
Classifier: Programming Language :: Python :: 3.6
Classifier: Programming Language :: Python :: 3.7
Classifier: Programming Language :: Python :: 3.8
Classifier: Programming Language :: Python :: 3.9
Requires-Python: >=3.6
License-File: LICENSE
Requires-Dist: numpy (>=1.16.6)
Requires-Dist: clubs (>=0.1.2)
Requires-Dist: gym (>=0.18.0)
